LICENSE
MANIFEST.in
README.rst
flask_log.py
setup.py
test_requirements.txt
flask_log.egg-info/PKG-INFO
flask_log.egg-info/SOURCES.txt
flask_log.egg-info/dependency_links.txt
flask_log.egg-info/not-zip-safe
flask_log.egg-info/requires.txt
flask_log.egg-info/top_level.txt