Metadata-Version: 1.1
Name: flask-log
Version: 0.1.0
Summary: Configure logging in flask applications
Home-page: http://github.com/mitodl/flask-log
Author: MIT ODL Engineering
Author-email: odl-engineering@mit.edu
License: BSD
Platform: any
Classifier: Environment :: Web Environment
Classifier: Intended Audience :: Developers
Classifier: License :: OSI Approved :: BSD License
Classifier: Operating System :: OS Independent
Classifier: Programming Language :: Python
Classifier: Topic :: Internet :: WWW/HTTP :: Dynamic Content
Classifier: Topic :: Software Development :: Libraries :: Python Modules
